LICENSE
MANIFEST.in
README.md
setup.cfg
setup.py
src/lognwrite/__init__.py
src/lognwrite/log_to_out.py
src/lognwrite.egg-info/PKG-INFO
src/lognwrite.egg-info/SOURCES.txt
src/lognwrite.egg-info/dependency_links.txt
src/lognwrite.egg-info/requires.txt
src/lognwrite.egg-info/top_level.txt