Metadata-Version: 2.1
Name: lognwrite
Version: 0.1.3
Home-page: https://github.com/malifpy/log-n-write
Author: Muhammad Alif Putra Yasa
Author-email: malifputrayasa@gmail.com
License: MIT
Keywords: log
License-File: LICENSE
